[
  {
    "ContainingType": "API_DBF_Demo.Controllers.DepartmentsController",
    "Method": "GetAllDepartments",
    "RelativePath": "api/Departments",
    "HttpMethod": "GET",
    "IsController": true,
    "Order": 0,
    "Parameters": [],
    "ReturnTypes": [
      {
        "Type": "System.Collections.Generic.IEnumerable\u00601[[API_DBF_Demo.DTO.DepartmentDTO, API_DBF_Demo, Version=1.0.0.0, Culture=neutral, PublicKeyToken=null]]",
        "MediaTypes": [
          "text/plain",
          "application/json",
          "text/json"
        ],
        "StatusCode": 200
      }
    ]
  },
  {
    "ContainingType": "API_DBF_Demo.Controllers.DepartmentsController",
    "Method": "AddDepartment",
    "RelativePath": "api/Departments",
    "HttpMethod": "POST",
    "IsController": true,
    "Order": 0,
    "Parameters": [
      {
        "Name": "departmentDTO",
        "Type": "API_DBF_Demo.DTO.DepartmentDTO",
        "IsRequired": true
      }
    ],
    "ReturnTypes": [
      {
        "Type": "API_DBF_Demo.DTO.DepartmentDTO",
        "MediaTypes": [
          "text/plain",
          "application/json",
          "text/json"
        ],
        "StatusCode": 200
      }
    ]
  },
  {
    "ContainingType": "API_DBF_Demo.Controllers.DepartmentsController",
    "Method": "GetDepartmentById",
    "RelativePath": "api/Departments/{id}",
    "HttpMethod": "GET",
    "IsController": true,
    "Order": 0,
    "Parameters": [
      {
        "Name": "id",
        "Type": "System.Int32",
        "IsRequired": true
      }
    ],
    "ReturnTypes": [
      {
        "Type": "API_DBF_Demo.Models.Department",
        "MediaTypes": [
          "text/plain",
          "application/json",
          "text/json"
        ],
        "StatusCode": 200
      }
    ]
  },
  {
    "ContainingType": "API_DBF_Demo.Controllers.DepartmentsController",
    "Method": "UpdateDepartment",
    "RelativePath": "api/Departments/{id}",
    "HttpMethod": "PUT",
    "IsController": true,
    "Order": 0,
    "Parameters": [
      {
        "Name": "id",
        "Type": "System.Int32",
        "IsRequired": true
      },
      {
        "Name": "departmentDTO",
        "Type": "API_DBF_Demo.DTO.DepartmentDTO",
        "IsRequired": true
      }
    ],
    "ReturnTypes": []
  },
  {
    "ContainingType": "API_DBF_Demo.Controllers.DepartmentsController",
    "Method": "DeleteDepartment",
    "RelativePath": "api/Departments/{id}",
    "HttpMethod": "DELETE",
    "IsController": true,
    "Order": 0,
    "Parameters": [
      {
        "Name": "id",
        "Type": "System.Int32",
        "IsRequired": true
      }
    ],
    "ReturnTypes": []
  },
  {
    "ContainingType": "API_DBF_Demo.Controllers.EmployeesController",
    "Method": "GetAllEmployees",
    "RelativePath": "api/Employees",
    "HttpMethod": "GET",
    "IsController": true,
    "Order": 0,
    "Parameters": [],
    "ReturnTypes": [
      {
        "Type": "System.Collections.Generic.IEnumerable\u00601[[API_DBF_Demo.DTO.EmployeeDTO, API_DBF_Demo, Version=1.0.0.0, Culture=neutral, PublicKeyToken=null]]",
        "MediaTypes": [
          "text/plain",
          "application/json",
          "text/json"
        ],
        "StatusCode": 200
      }
    ]
  },
  {
    "ContainingType": "API_DBF_Demo.Controllers.EmployeesController",
    "Method": "AddEmployee",
    "RelativePath": "api/Employees",
    "HttpMethod": "POST",
    "IsController": true,
    "Order": 0,
    "Parameters": [
      {
        "Name": "employeeDTO",
        "Type": "API_DBF_Demo.DTO.EmployeeDTO",
        "IsRequired": true
      }
    ],
    "ReturnTypes": [
      {
        "Type": "API_DBF_Demo.DTO.EmployeeDTO",
        "MediaTypes": [
          "text/plain",
          "application/json",
          "text/json"
        ],
        "StatusCode": 200
      }
    ]
  },
  {
    "ContainingType": "API_DBF_Demo.Controllers.EmployeesController",
    "Method": "GetEmployeeById",
    "RelativePath": "api/Employees/{id}",
    "HttpMethod": "GET",
    "IsController": true,
    "Order": 0,
    "Parameters": [
      {
        "Name": "id",
        "Type": "System.Int32",
        "IsRequired": true
      }
    ],
    "ReturnTypes": [
      {
        "Type": "API_DBF_Demo.DTO.EmployeeDTO",
        "MediaTypes": [
          "text/plain",
          "application/json",
          "text/json"
        ],
        "StatusCode": 200
      }
    ]
  },
  {
    "ContainingType": "API_DBF_Demo.Controllers.EmployeesController",
    "Method": "UpdateEmployee",
    "RelativePath": "api/Employees/{id}",
    "HttpMethod": "PUT",
    "IsController": true,
    "Order": 0,
    "Parameters": [
      {
        "Name": "id",
        "Type": "System.Int32",
        "IsRequired": true
      },
      {
        "Name": "employeeDTO",
        "Type": "API_DBF_Demo.DTO.EmployeeDTO",
        "IsRequired": true
      }
    ],
    "ReturnTypes": []
  },
  {
    "ContainingType": "API_DBF_Demo.Controllers.EmployeesController",
    "Method": "DeleteEmployee",
    "RelativePath": "api/Employees/{id}",
    "HttpMethod": "DELETE",
    "IsController": true,
    "Order": 0,
    "Parameters": [
      {
        "Name": "id",
        "Type": "System.Int32",
        "IsRequired": true
      }
    ],
    "ReturnTypes": []
  },
  {
    "ContainingType": "API_DBF_Demo.Controllers.WeatherForecastController",
    "Method": "Get",
    "RelativePath": "WeatherForecast",
    "HttpMethod": "GET",
    "IsController": true,
    "Order": 0,
    "Parameters": [],
    "ReturnTypes": [
      {
        "Type": "System.Collections.Generic.IEnumerable\u00601[[API_DBF_Demo.WeatherForecast, API_DBF_Demo, Version=1.0.0.0, Culture=neutral, PublicKeyToken=null]]",
        "MediaTypes": [
          "text/plain",
          "application/json",
          "text/json"
        ],
        "StatusCode": 200
      }
    ],
    "EndpointName": "GetWeatherForecast"
  }
]